tencentcloud/__init__.py
tencentcloud/chdfs/__init__.py
tencentcloud/chdfs/v20190718/__init__.py
tencentcloud/chdfs/v20190718/chdfs_client.py
tencentcloud/chdfs/v20190718/chdfs_client_async.py
tencentcloud/chdfs/v20190718/errorcodes.py
tencentcloud/chdfs/v20190718/models.py
tencentcloud/chdfs/v20201112/__init__.py
tencentcloud/chdfs/v20201112/chdfs_client.py
tencentcloud/chdfs/v20201112/chdfs_client_async.py
tencentcloud/chdfs/v20201112/errorcodes.py
tencentcloud/chdfs/v20201112/models.py
tencentcloud_sdk_python_chdfs-3.1.19.dist-info/METADATA
tencentcloud_sdk_python_chdfs-3.1.19.dist-info/WHEEL
tencentcloud_sdk_python_chdfs-3.1.19.dist-info/top_level.txt
tencentcloud_sdk_python_chdfs-3.1.19.dist-info/RECORD
